usajobsapi/__init__.py
usajobsapi/__main__.py
usajobsapi/_version.py
usajobsapi/cli.py
usajobsapi/client.py
usajobsapi/utils.py
usajobsapi/endpoints/__init__.py
usajobsapi/endpoints/_validators.py
usajobsapi/endpoints/announcementtext.py
usajobsapi/endpoints/historicjoa.py
usajobsapi/endpoints/search.py
python_usajobsapi-1.0.2.dist-info/METADATA
python_usajobsapi-1.0.2.dist-info/WHEEL
python_usajobsapi-1.0.2.dist-info/entry_points.txt
python_usajobsapi-1.0.2.dist-info/licenses/LICENSE
python_usajobsapi-1.0.2.dist-info/RECORD
