Metadata-Version: 2.4
Name: python-usajobsapi
Version: 1.0.2
Summary: A Python wrapper for the USA Jobs REST API.
Project-URL: Homepage, https://paddy74.github.io/python-usajobsapi/
Project-URL: Changelog, https://paddy74.github.io/python-usajobsapi/about/changelog/
Project-URL: Documentation, https://paddy74.github.io/python-usajobsapi/
Project-URL: Source, https://github.com/paddy74/python-usajobsapi/
License:                     GNU GENERAL PUBLIC LICENSE
License-File: LICENSE
Keywords: api,wrapper
Requires-Python: >=3.11
Requires-Dist: pydantic>=2.11.7
Requires-Dist: requests>=2.32.5
Provides-Extra: build
Requires-Dist: uv~=0.8.17; extra == 'build'
